pkrhistoryreader/__init__.py
pkrhistoryreader/app.py
pkrhistoryreader/reader.py
pkrhistoryreader-0.3.0.dist-info/LICENSE.txt
pkrhistoryreader-0.3.0.dist-info/METADATA
pkrhistoryreader-0.3.0.dist-info/WHEEL
pkrhistoryreader-0.3.0.dist-info/top_level.txt
pkrhistoryreader-0.3.0.dist-info/RECORD
