Metadata-Version: 2.1
Name: pkrhistoryreader
Version: 0.3.0
Summary: A Poker Package to read poker history files from S3 bucket
Home-page: https://github.com/manggy94/PokerHistoryreader
Author: Alexandre MANGWA
Author-email: alex.mangwa@gmail.com
License: UNKNOWN
Keywords: poker pkrhistory history pkr pkrhistoryreader pokerhistory reader
Platform: UNKNOWN
Classifier: Development Status :: 4 - Beta
Classifier: Intended Audience :: Developers
Classifier: License :: OSI Approved :: MIT License
Classifier: Natural Language :: English
Classifier: Natural Language :: French
Classifier: Programming Language :: Python
Classifier: Programming Language :: Python :: 3
Classifier: Topic :: Games/Entertainment
Classifier: Topic :: Games/Entertainment :: Board Games
License-File: LICENSE.txt
Requires-Dist: boto3
Requires-Dist: python-dotenv
